aioresilience/__init__.py
aioresilience/adaptive_concurrency.py
aioresilience/backpressure.py
aioresilience/bulkhead.py
aioresilience/circuit_breaker.py
aioresilience/config.py
aioresilience/fallback.py
aioresilience/logging.py
aioresilience/py.typed
aioresilience/retry.py
aioresilience/timeout.py
aioresilience/events/__init__.py
aioresilience/events/bus.py
aioresilience/events/emitter.py
aioresilience/events/types.py
aioresilience/exceptions/__init__.py
aioresilience/exceptions/base.py
aioresilience/exceptions/config.py
aioresilience/exceptions/errors.py
aioresilience/exceptions/handler.py
aioresilience/exceptions/reasons.py
aioresilience/integrations/__init__.py
aioresilience/integrations/aiohttp/__init__.py
aioresilience/integrations/aiohttp/decorators.py
aioresilience/integrations/aiohttp/middleware.py
aioresilience/integrations/aiohttp/utils.py
aioresilience/integrations/fastapi/__init__.py
aioresilience/integrations/fastapi/adaptive_concurrency.py
aioresilience/integrations/fastapi/backpressure.py
aioresilience/integrations/fastapi/bulkhead.py
aioresilience/integrations/fastapi/circuit_breaker.py
aioresilience/integrations/fastapi/composite.py
aioresilience/integrations/fastapi/decorators.py
aioresilience/integrations/fastapi/dependencies.py
aioresilience/integrations/fastapi/fallback.py
aioresilience/integrations/fastapi/load_shedding.py
aioresilience/integrations/fastapi/retry.py
aioresilience/integrations/fastapi/timeout.py
aioresilience/integrations/fastapi/utils.py
aioresilience/integrations/sanic/__init__.py
aioresilience/integrations/sanic/decorators.py
aioresilience/integrations/sanic/middleware.py
aioresilience/integrations/sanic/utils.py
aioresilience/load_shedding/__init__.py
aioresilience/load_shedding/basic.py
aioresilience/load_shedding/system.py
aioresilience/rate_limiting/__init__.py
aioresilience/rate_limiting/local.py
aioresilience/rate_limiting/redis.py
aioresilience-0.2.1.dist-info/licenses/LICENSE
aioresilience-0.2.1.dist-info/METADATA
aioresilience-0.2.1.dist-info/WHEEL
aioresilience-0.2.1.dist-info/top_level.txt
aioresilience-0.2.1.dist-info/RECORD
