Metadata-Version: 2.4
Name: aioresilience
Version: 0.2.1
Summary: Async resilience patterns for Python - Circuit breakers, rate limiting, and more
Author-email: xonming <xonming@users.noreply.github.com>
License: MIT License
Project-URL: Homepage, https://github.com/xonming/aioresilience
Project-URL: Documentation, https://github.com/xonming/aioresilience#readme
Project-URL: Repository, https://github.com/xonming/aioresilience
Project-URL: Issues, https://github.com/xonming/aioresilience/issues
Project-URL: Changelog, https://github.com/xonming/aioresilience/blob/main/CHANGELOG.md
Keywords: async,asyncio,resilience,circuit-breaker,rate-limiting,backpressure,fault-tolerance
Classifier: Development Status :: 3 - Alpha
Classifier: Intended Audience :: Developers
Classifier: Operating System :: OS Independent
Classifier: Programming Language :: Python :: 3
Classifier: Programming Language :: Python :: 3.9
Classifier: Programming Language :: Python :: 3.10
Classifier: Programming Language :: Python :: 3.11
Classifier: Programming Language :: Python :: 3.12
Classifier: Programming Language :: Python :: 3.13
Classifier: Topic :: Software Development :: Libraries :: Python Modules
Classifier: Framework :: AsyncIO
Classifier: Framework :: FastAPI
Classifier: Typing :: Typed
Requires-Python: >=3.9
License-File: LICENSE
Requires-Dist: aiolimiter>=1.0.0
Provides-Extra: redis
Requires-Dist: redis>=4.5.0; extra == "redis"
Provides-Extra: system
Requires-Dist: psutil>=5.9.0; extra == "system"
Provides-Extra: fastapi
Requires-Dist: fastapi>=0.100.0; extra == "fastapi"
Requires-Dist: starlette>=0.27.0; extra == "fastapi"
Provides-Extra: sanic
Requires-Dist: sanic>=23.0.0; extra == "sanic"
Requires-Dist: sanic-testing>=23.3.0; extra == "sanic"
Provides-Extra: aiohttp
Requires-Dist: aiohttp>=3.8.0; extra == "aiohttp"
Provides-Extra: integrations
Requires-Dist: fastapi>=0.100.0; extra == "integrations"
Requires-Dist: starlette>=0.27.0; extra == "integrations"
Requires-Dist: sanic>=23.0.0; extra == "integrations"
Requires-Dist: sanic-testing>=23.3.0; extra == "integrations"
Requires-Dist: aiohttp>=3.8.0; extra == "integrations"
Provides-Extra: dev
Requires-Dist: pytest>=7.4.0; extra == "dev"
Requires-Dist: pytest-asyncio>=0.21.0; extra == "dev"
Requires-Dist: pytest-cov>=4.1.0; extra == "dev"
Requires-Dist: pytest-timeout>=2.1.0; extra == "dev"
Requires-Dist: pytest-benchmark>=4.0.0; extra == "dev"
Requires-Dist: black>=23.0.0; extra == "dev"
Requires-Dist: flake8>=6.0.0; extra == "dev"
Requires-Dist: mypy>=1.5.0; extra == "dev"
Requires-Dist: isort>=5.12.0; extra == "dev"
Requires-Dist: httpx>=0.24.0; extra == "dev"
Requires-Dist: build>=0.10.0; extra == "dev"
Requires-Dist: twine>=4.0.0; extra == "dev"
Requires-Dist: wheel>=0.40.0; extra == "dev"
Provides-Extra: all
Requires-Dist: redis>=4.5.0; extra == "all"
Requires-Dist: psutil>=5.9.0; extra == "all"
Requires-Dist: fastapi>=0.100.0; extra == "all"
Requires-Dist: starlette>=0.27.0; extra == "all"
Requires-Dist: sanic>=23.0.0; extra == "all"
Requires-Dist: sanic-testing>=23.3.0; extra == "all"
Requires-Dist: aiohttp>=3.8.0; extra == "all"
Dynamic: license-file
